senschar/__init__.py
senschar/api.py
senschar/cli.py
senschar/cmdserver.py
senschar/console.py
senschar/database.py
senschar/database_console.py
senschar/database_server.py
senschar/exceptions.py
senschar/fits.py
senschar/header.py
senschar/image.py
senschar/image_focalplane.py
senschar/image_headers.py
senschar/image_io.py
senschar/logger.py
senschar/parameters.py
senschar/parameters_console.py
senschar/parameters_server.py
senschar/plot.py
senschar/remote_logger.py
senschar/scripts.py
senschar/server.py
senschar/shortcuts.py
senschar/sockets.py
senschar/utils.py
senschar/utils_console.py
senschar/scripts/__init__.py
senschar/scripts/centroids.py
senschar/scripts/check_bits.py
senschar/scripts/display_files.py
senschar/scripts/get_pressures.py
senschar/scripts/get_temperatures.py
senschar/scripts/plot_header_times.py
senschar/scripts/plot_images.py
senschar/scripts/plot_keywords.py
senschar/scripts/plot_log_temps.py
senschar/scripts/readnoise_correction.py
senschar/scripts/scan_wavelengths.py
senschar/scripts/scripts.py
senschar/scripts/show_histogram.py
senschar/scripts/show_sequence_keywords.py
senschar/scripts/show_sequence_stats.py
senschar/scripts/test_arc_controller.py
senschar/scripts/test_filters.py
senschar/scripts/test_gain_stability.py
senschar/scripts/test_instrument.py
senschar/scripts/test_mag_controller.py
senschar/scripts/test_reset.py
senschar/scripts/test_server.py
senschar/scripts/test_shutter.py
senschar/scripts/test_temperatures.py
senschar/scripts/test_wavelengths.py
senschar/scripts/threshold_image.py
senschar/testers/__init__.py
senschar/testers/basetester.py
senschar/testers/bias.py
senschar/testers/dark.py
senschar/testers/defects.py
senschar/testers/detcal.py
senschar/testers/detchar.py
senschar/testers/eper.py
senschar/testers/fe55.py
senschar/testers/gain.py
senschar/testers/gainmap.py
senschar/testers/linearity.py
senschar/testers/prnu.py
senschar/testers/ptc.py
senschar/testers/qe.py
senschar/testers/ramp.py
senschar-25.0.dist-info/entry_points.txt
senschar-25.0.dist-info/licenses/LICENSE
senschar-25.0.dist-info/WHEEL
senschar-25.0.dist-info/METADATA
senschar-25.0.dist-info/RECORD
