Metadata-Version: 2.4
Name: senschar
Version: 25.0
Summary: Scientific sensor image characterization package
Keywords: ccd,imaging,astronomy,sensors
Author: Michael Lesser
Author-email: mlesser@arizona.edu
Requires-Python: >= 3.10
License-File: LICENSE
Requires-Dist: loguru
Requires-Dist: numpy
Requires-Dist: astropy
Requires-Dist: psutil
Requires-Dist: fastapi
Requires-Dist: uvicorn
Requires-Dist: jinja2
Requires-Dist: dash
Requires-Dist: dash-bootstrap-components
Requires-Dist: dash_daq
Requires-Dist: pandas
Requires-Dist: scipy
Requires-Dist: matplotlib
Requires-Dist: pyside6
Requires-Dist: pdfkit
Requires-Dist: markdown
Requires-Dist: pypdf
Requires-Dist: pywin32; sys_platform == 'win32'
Requires-Dist: mkdocstrings[python]>=0.18
Project-URL: Documentation, https://senschar.readthedocs.io/
Project-URL: Repository, https://github.com/mplesser/senschar/
